minion_agent/__init__.py
minion_agent/agent.py
minion_agent/logging.py
minion_agent/config/__init__.py
minion_agent/config/settings.py
minion_agent/frameworks/browser_use.py
minion_agent/frameworks/google.py
minion_agent/frameworks/minion.py
minion_agent/frameworks/minion_agent.py
minion_agent/frameworks/smolagents.py
minion_agent/instructions/__init__.py
minion_agent/instructions/imports.py
minion_agent/providers/__init__.py
minion_agent/providers/adapters.py
minion_agent/tools/__init__.py
minion_agent/tools/adapters.py
minion_agent/tools/base.py
minion_agent/tools/browser_tool.py
minion_agent/tools/decorators.py
minion_agent/tools/mcp.py
minion_agent/tools/user_interaction.py
minion_agent/tools/web_browsing.py
minion_agent/tools/wrappers.py
minion_agent/utils/__init__.py
minion_agent/utils/logging.py
minion_agentic-0.1.1.dist-info/METADATA
minion_agentic-0.1.1.dist-info/WHEEL
minion_agentic-0.1.1.dist-info/licenses/LICENSE
minion_agentic-0.1.1.dist-info/RECORD
